{
    "标题": [
        "天津市河北区人民政府月牙河街道办事处机关",
        "天津市河北区人民政府月牙河街道办事处渣土清运服务项目",
        "(项目编号:ZXZB2020-F-012)竞争性磋商公告"
    ],
    "项目概况": "天津市河北区人民政府月牙河街道办事处渣土清运服务项目 采购项目的潜在供应商应在 天津河北区王串场街容彩里2号楼1号底商 获取采购文件，并于 2020年07月29日 09点30分 （北京时间）前提交响应文件。",
    "一、项目基本情况": {
        "项目编号": "ZXZB2020-F-012",
        "项目名称": "天津市河北区人民政府月牙河街道办事处渣土清运服务项目",
        "采购方式": "竞争性磋商",
        "预算金额": "181.012万元",
        "最高限价": "181.012万元",
        "采购需求": {
            "1": {
                "包号": "第1包",
                "是否设置最高限额": "否",
                "预算（万元）": "181.012",
                "最高限额（万元）": "181.012",
                "采购目录": "其他城镇公共卫生服务",
                "采购需求": "详见招标文件"
            }
        },
        "合同履行期限": "签订合同之日起1年的服务期",
        "其他": "本项目不接受联合体参与，本项目不接受进口产品"
    },
    "二、申请人的资格要求": {
        "1": "1.满足《中华人民共和国政府采购法》第二十二条规定；",
        "2": "2.落实政府采购政策需满足的资格要求：项目需要落实的政府采购政策 （一）根据《政府采购促进中小企业发展暂行办法》（财库[2011]181号）规定，本项目专门面向小型、微型企业采购。 （二）根据财政部发布的《关于政府采购支持监狱企业发展有关问题的通知》规定，监狱企业视同小型、微型企业。 （三）根据财政部、民政部、中国残疾人联合会发布的《关于促进残疾人就业政府采购政策的通知》规定，残疾人福利性单位视同小型、微型企业。 注：中小微企业以投标人填写的《中小企业声明函》为判定标准，残疾人福利性单位以投标人填写的《残疾人福利性单位声明函》为判定标准，监狱企业须投标人提供由省级以上监狱管理局、戒毒管理局（含新疆生产建设兵团）出具的属于监狱企业的证明文件，否则不予认定。以上政策不重复享受。 （四）按照《财政部关于在政府采购活动中查询及使用信用记录有关问题的通知》（财库〔2016〕125号）的要求，根据开标当日第一阶段截止时间“信用中国”网站（www.creditchina.gov.cn）、中国政府采购网（www.ccgp.gov.cn）的信息，对列入失信被执行人、重大税收违法案件当事人名单、政府采购严重违法失信行为记录名单及其他不符合《中华人民共和国政府采购法》第二十二条规定条件的供应商，拒绝参与政府采购活动，同时对信用信息查询记录和证据进行打印存档。 供应商资格要求： （一）供应商应具备《中华人民共和国政府采购法》第二十二条第一款规定的条件，提供以下材料： 1.营业执照副本或事业单位法人证书或民办非企业单位登记证书或社会团体法人登记证书或基金会法人登记证书扫描件； 2.财务状况报告等相关材料： A.经第三方会计师事务所审计的2018年度或2019年度财务报告扫描件。 B.2019年度或2020年度银行出具的资信证明扫描件。 注：A、B两项提供任意一项均可。 3.2019年度或2020年度至少1个月的依法缴纳税收和社会保险费的相关证明材料扫描件； 4.提交响应文件截止日前3年在经营活动中没有重大违法记录的书面声明（截至提交响应文件截止日成立不足3年的供应商可提供自成立以来无重大违法记录的书面声明）。 （二）本项目不接受联合体参与磋商。 （三）本项目专门面向小微企业采购，提供《小微企业声明函》。 本项目专门面向小型、微型企业采购;",
        "3": "3.本项目的特定资格要求：本项目不接受联合体参与磋商"
    },
    "三、获取采购文件": {
        "时间": " 2020年07月17日 到 2020年07月24日 ，每天上午09:00至12:00，下午14:00至16:00（北京时间，法定节假日除外）",
        "地点": "天津河北区王串场街容彩里2号楼1号底商",
        "方式": "供应商须在《天津市政府采购网》（网址:http://tjgp.cz.tj.gov.cn/）上完成注册并成为合格供应商；供应商须携带营业执照扫描件加盖公章、报名人授权委托书及报名人的身份证扫描件加盖公章，现场发售领取。",
        "售价": "500元"
    },
    "四、响应文件提交": {
        "截止时间": " 2020年07月29日 09点30分 （北京时间）",
        "地点": "天津河北区王串场街容彩里2号楼1号底商"
    },
    "五、开启": {
        "时间": " 2020年07月29日 09点30分 （北京时间）",
        "地点": "天津河北区王串场街容彩里2号楼1号底商"
    },
    "六、公告期限": {
        "1": "自本公告发布之日起3个工作日。"
    },
    "七、其他补充事宜": {},
    "八、联系方式": {
        "采购人信息,名称": "天津市河北区人民政府月牙河街道办事处机关",
        "采购人信息,地址": "天津市河北区靖江路义江道36号",
        "采购人信息,联系方式": "022-26154114",
        "采购代理机构信息,名称": "天津中新招标代理有限公司",
        "采购代理机构信息,地址": "天津河北区王串场街容彩里2号楼1号底商",
        "采购代理机构信息,联系方式": "18622961909",
        "项目联系方式,项目联系人": "李老师",
        "项目联系方式,电话": "18622961909"
    }
}